{
  "top" : "Хочу заказать верх (Платье, блузка, жакет, рубашка)",
  "skirt": "Хочу заказать низ Юбка",
  "throusres": "Хочу заказать низ Брюки",
  "menedger": "Связаться с менеджером",
  "perereg": "Зарегистрироваться заново",
  "admin": "Открываю панель управления...\\nбип-буп-бип",
  "oldSIze": "Использовать старые мерки",
  "makeSize": "Сделаем мерки",
  "standartSize": "Стандартный размер",
  "back": "Назад",
  "order": "Что вы хотите заказать?",
  "parametrCheck": "🥺Не похоже на ваши параметры. Попробуйте еще раз",
  "fileCheck": "\uD83E\uDD7AНе похоже на нужный формат. Загрузи фотографию в обычном формате теллеграмма или в виде файла с расширением jpg/jpeg/png",
  "clothes" : "Заказать одежду",
  "lists": "Получить список всех пользователей",
  "menu" : "В меню",
  "size": "Давайте снимим с вас мерки",
  "action": "Выберите действие",
  "problem": "Напишите свою проблему, или нажмите кнопку 'Назад'",
  "perereg" : "Вы точно хотите пройти процесс регистрации заново?",
  "number" : "Предоставить номер телефона",
  "getNumber": "Здравствуйте, предоставьте свой номер телефона",
  "repeatMenu":"Возвращаю вас в меню...",
  "name" : "Напишите ваше имя",
  "nameCheck": "\uD83E\uDD7AНе похоже на имя. Попробуйте еще раз",
  "lastName": "Напишите вашу фамилию",
  "lastNameCheck": "\uD83E\uDD7AНе похоже на фамилию. Попробуйте еще раз",
  "age": "Напишите свой возраст",
  "ageCheck": "\uD83E\uDD7AНе похоже на возраст. Попробуйте еще раз",
  "region": "Выберите свой регион",
  "yourSize": "Какой размер одежды вы носите?",
  "finishReg": "Регистрация завершена",
  "skip": "Пропустить",
  "front": "Загрузите фото в полный рост спереди",
  "behind": "Загрузите фото в полный рост сзади",
  "profile": "Загрузите фото в полный рост в профиль",
  "product": "Загрузите одно-два фото желаемого изделия",
  "start": "Начать",
  "please": "Пожалуйста, измерьте фигуру самостоятельно или при помощи другого человека, следуя инструкции.",
  "photoComplete": "Фото получено",
  "connect": "Благодарим Вас! С вами свяжется наш менеджер в течении 1 часа."






}